ovl/__init__.py
ovl/camera/__init__.py
ovl/camera/camera.py
ovl/camera/camera_calibration.py
ovl/camera/camera_configuration.py
ovl/camera/camera_properties.py
ovl/connections/__init__.py
ovl/connections/connection.py
ovl/connections/http_connection.py
ovl/connections/network_location.py
ovl/connections/network_tables_connection.py
ovl/connections/network_validation.py
ovl/connections/serial_connection.py
ovl/detectors/__init__.py
ovl/detectors/detector.py
ovl/detectors/haar_cascade_detector.py
ovl/detectors/threshold_detector.py
ovl/direction_modifiers/__init__.py
ovl/direction_modifiers/direction_modifier.py
ovl/direction_modifiers/stop_if_close_modifier.py
ovl/directions/__init__.py
ovl/directions/directing_functions.py
ovl/directions/director.py
ovl/directions/target_selector.py
ovl/exceptions/__init__.py
ovl/exceptions/exceptions.py
ovl/image_filters/__init__.py
ovl/image_filters/image_filter.py
ovl/image_filters/image_filters.py
ovl/image_filters/kernels.py
ovl/image_utilities/__init__.py
ovl/image_utilities/display_contours.py
ovl/image_utilities/display_image.py
ovl/image_utilities/is_image.py
ovl/image_utilities/naming_conventions.py
ovl/image_utilities/open_image.py
ovl/image_utilities/photo_array.py
ovl/morphological_functions/__init__.py
ovl/morphological_functions/morphological_functions.py
ovl/ovl_math/__init__.py
ovl/ovl_math/contours.py
ovl/ovl_math/geometry.py
ovl/ovl_math/image.py
ovl/ovl_math/math_3d.py
ovl/ovl_math/shape_fill_ratios.py
ovl/partials/__init__.py
ovl/partials/filter_applier.py
ovl/partials/keyword_partial.py
ovl/partials/reverse_partial.py
ovl/target_filters/__init__.py
ovl/target_filters/contour_filters.py
ovl/target_filters/predicate_target_filter.py
ovl/target_filters/shape_filer_constants.py
ovl/target_filters/sorter_helper_functions.py
ovl/target_filters/sorters.py
ovl/target_filters/target_filter.py
ovl/target_filters/shape_filters/__init__.py
ovl/target_filters/shape_filters/circle_filter.py
ovl-2022.1.3.dist-info/LICENSE
ovl-2022.1.3.dist-info/METADATA
ovl-2022.1.3.dist-info/WHEEL
ovl-2022.1.3.dist-info/top_level.txt
ovl-2022.1.3.dist-info/RECORD
