Metadata-Version: 2.1
Name: ovl
Version: 2022.1.3
Summary: A modular and versatile Python package for computer vision object detection pipelines tailored for robotics applications
Home-page: https://github.com/SerpentBit/ovl
Author: SerpentBit
Author-email: ovl.contact.help@gmail.com
License: apache-2.0
Platform: UNKNOWN
Classifier: Development Status :: 4 - Beta
Classifier: Intended Audience :: Education
Classifier: Intended Audience :: Developers
Classifier: Intended Audience :: Science/Research
Classifier: License :: OSI Approved :: Apache Software License
Classifier: Programming Language :: Python
Classifier: Programming Language :: Python :: 3.7
Classifier: Programming Language :: Python :: 3.8
Classifier: Programming Language :: Python :: 3.9
Classifier: Programming Language :: Python :: 3.10
Classifier: Topic :: Scientific/Engineering :: Image Recognition
Classifier: Operating System :: POSIX :: Linux
Classifier: Operating System :: Microsoft :: Windows
License-File: LICENSE
Requires-Dist: numpy
Provides-Extra: connections
Requires-Dist: pyserial ; extra == 'connections'
Requires-Dist: requests ; extra == 'connections'
Provides-Extra: cv
Requires-Dist: opencv-python ; extra == 'cv'
Provides-Extra: frc
Requires-Dist: pynetworktables ; extra == 'frc'
